CONTRIBUTING.md
MANIFEST.in
README.rst
setup.py
docs/HISTORY.txt
docs/LICENSE.GPL
docs/LICENSE.txt
eea/__init__.py
eea.api.redirector.egg-info/PKG-INFO
eea.api.redirector.egg-info/SOURCES.txt
eea.api.redirector.egg-info/dependency_links.txt
eea.api.redirector.egg-info/entry_points.txt
eea.api.redirector.egg-info/namespace_packages.txt
eea.api.redirector.egg-info/not-zip-safe
eea.api.redirector.egg-info/requires.txt
eea.api.redirector.egg-info/top_level.txt
eea/api/__init__.py
eea/api/redirector/README.txt
eea/api/redirector/__init__.py
eea/api/redirector/configure.zcml
eea/api/redirector/interfaces.py
eea/api/redirector/profiles.zcml
eea/api/redirector/setuphandlers.py
eea/api/redirector/version.txt
eea/api/redirector/browser/__init__.py
eea/api/redirector/browser/configure.zcml
eea/api/redirector/browser/controlpanel.py
eea/api/redirector/locales/__init__.py
eea/api/redirector/locales/eea.pot
eea/api/redirector/locales/plone-manual.pot
eea/api/redirector/locales/update.sh
eea/api/redirector/locales/bg/LC_MESSAGES/eea.mo
eea/api/redirector/locales/bg/LC_MESSAGES/eea.po
eea/api/redirector/locales/bg/LC_MESSAGES/plone.mo
eea/api/redirector/locales/bg/LC_MESSAGES/plone.po
eea/api/redirector/locales/cs/LC_MESSAGES/eea.mo
eea/api/redirector/locales/cs/LC_MESSAGES/eea.po
eea/api/redirector/locales/cs/LC_MESSAGES/plone.mo
eea/api/redirector/locales/cs/LC_MESSAGES/plone.po
eea/api/redirector/locales/da/LC_MESSAGES/eea.mo
eea/api/redirector/locales/da/LC_MESSAGES/eea.po
eea/api/redirector/locales/da/LC_MESSAGES/plone.mo
eea/api/redirector/locales/da/LC_MESSAGES/plone.po
eea/api/redirector/locales/de/LC_MESSAGES/eea.mo
eea/api/redirector/locales/de/LC_MESSAGES/eea.po
eea/api/redirector/locales/de/LC_MESSAGES/plone.mo
eea/api/redirector/locales/de/LC_MESSAGES/plone.po
eea/api/redirector/locales/el/LC_MESSAGES/eea.mo
eea/api/redirector/locales/el/LC_MESSAGES/eea.po
eea/api/redirector/locales/el/LC_MESSAGES/plone.mo
eea/api/redirector/locales/el/LC_MESSAGES/plone.po
eea/api/redirector/locales/en/LC_MESSAGES/eea.mo
eea/api/redirector/locales/en/LC_MESSAGES/eea.po
eea/api/redirector/locales/en/LC_MESSAGES/plone.mo
eea/api/redirector/locales/en/LC_MESSAGES/plone.po
eea/api/redirector/locales/es/LC_MESSAGES/eea.mo
eea/api/redirector/locales/es/LC_MESSAGES/eea.po
eea/api/redirector/locales/es/LC_MESSAGES/plone.mo
